lib/__init__.py
lib/models.py
lib/utils.py
lib/tke/__init__.py
lib/tke/tke.py
lib/tke/tke_base.py
tencentcloud/__init__.py
tencentcloud/aai/__init__.py
tencentcloud/aai/v20180522/__init__.py
tencentcloud/aai/v20180522/aai_client.py
tencentcloud/aai/v20180522/errorcodes.py
tencentcloud/aai/v20180522/models.py
tencentcloud/aca/__init__.py
tencentcloud/aca/v20210323/__init__.py
tencentcloud/aca/v20210323/aca_client.py
tencentcloud/aca/v20210323/errorcodes.py
tencentcloud/aca/v20210323/models.py
tencentcloud/acp/__init__.py
tencentcloud/acp/v20220105/__init__.py
tencentcloud/acp/v20220105/acp_client.py
tencentcloud/acp/v20220105/errorcodes.py
tencentcloud/acp/v20220105/models.py
tencentcloud/advisor/__init__.py
tencentcloud/advisor/v20200721/__init__.py
tencentcloud/advisor/v20200721/advisor_client.py
tencentcloud/advisor/v20200721/errorcodes.py
tencentcloud/advisor/v20200721/models.py
tencentcloud/af/__init__.py
tencentcloud/af/v20200226/__init__.py
tencentcloud/af/v20200226/af_client.py
tencentcloud/af/v20200226/errorcodes.py
tencentcloud/af/v20200226/models.py
tencentcloud/afc/__init__.py
tencentcloud/afc/v20200226/__init__.py
tencentcloud/afc/v20200226/afc_client.py
tencentcloud/afc/v20200226/errorcodes.py
tencentcloud/afc/v20200226/models.py
tencentcloud/aiart/__init__.py
tencentcloud/aiart/v20221229/__init__.py
tencentcloud/aiart/v20221229/aiart_client.py
tencentcloud/aiart/v20221229/errorcodes.py
tencentcloud/aiart/v20221229/models.py
tencentcloud/ame/__init__.py
tencentcloud/ame/v20190916/__init__.py
tencentcloud/ame/v20190916/ame_client.py
tencentcloud/ame/v20190916/errorcodes.py
tencentcloud/ame/v20190916/models.py
tencentcloud/ams/__init__.py
tencentcloud/ams/v20200608/__init__.py
tencentcloud/ams/v20200608/ams_client.py
tencentcloud/ams/v20200608/errorcodes.py
tencentcloud/ams/v20200608/models.py
tencentcloud/ams/v20201229/__init__.py
tencentcloud/ams/v20201229/ams_client.py
tencentcloud/ams/v20201229/errorcodes.py
tencentcloud/ams/v20201229/models.py
tc_auto-0.1.1.dist-info/METADATA
tc_auto-0.1.1.dist-info/WHEEL
tc_auto-0.1.1.dist-info/top_level.txt
tc_auto-0.1.1.dist-info/RECORD
